{
  "smithery_auto_push": {
    "enabled": true,
    "description": "Push automatique via Smithery CLI après chaque commit & push",
    "workflow": {
      "trigger": "git post-commit hook",
      "steps": [
        "Vérification de l'environnement git",
        "Vérification de l'installation Smithery CLI",
        "Vérification de la connexion Smithery",
        "Construction du projet (smithery build)",
        "Push automatique (smithery push/deploy)"
      ]
    },
    "files": {
      "script": "scripts/post-commit.sh",
      "hook": ".git/hooks/post-commit",
      "config": "smithery.yaml",
      "documentation": "SMITHERY_AUTO_PUSH.md"
    },
    "prerequisites": [
      "Smithery CLI installé",
      "Connexion Smithery active",
      "Projet configuré avec smithery.yaml"
    ],
    "commands": {
      "install_smithery": "npm install -g @smithery/cli",
      "login_smithery": "smithery login",
      "manual_build": "smithery build",
      "manual_push": "smithery push",
      "check_status": "smithery list"
    },
    "created": "2024-12-19",
    "version": "1.0.0"
  }
}
